array_prop_pack/__init__.py
array_prop_pack/array_prop.py
array_prop_pack-0.0.1.dist-info/METADATA
array_prop_pack-0.0.1.dist-info/WHEEL
array_prop_pack-0.0.1.dist-info/top_level.txt
array_prop_pack-0.0.1.dist-info/RECORD
