Metadata-Version: 2.1
Name: array-prop-pack
Version: 0.0.1
Summary: Some properties of an array
Home-page: UNKNOWN
Author: luca
Author-email: 
License: UNKNOWN
Platform: UNKNOWN
Requires-Python: >=3.5
Requires-Dist: numpy
